CHANGELOG.md
LICENSE
MANIFEST.in
README.md
pyproject.toml
setup.cfg
setup.py
boakboak/__init__.py
boakboak/__main__.py
boakboak.egg-info/PKG-INFO
boakboak.egg-info/SOURCES.txt
boakboak.egg-info/dependency_links.txt
boakboak.egg-info/entry_points.txt
boakboak.egg-info/requires.txt
boakboak.egg-info/top_level.txt
boakboak/apps/__init__.py
boakboak/apps/archive.yml
boakboak/apps/test.yml
boakboak/src/__init__.py
boakboak/src/boakboak.py
boakboak/src/clean_params.py
boakboak/src/executable.py
boakboak/src/logger.py
boakboak/src/params.py
boakboak/src/settings.py
boakboak/test/__init__.py
boakboak/test/boak_unittest.py
boakboak/test/test_executable.py
boakboak/test/test_params.py