Metadata-Version: 2.1
Name: boakboak
Version: 1.1.1
Summary: Plugin service that runs your python programs anywhere without install.
Home-page: https://gitlab.com/larsmielke2/boakboak
Author: Lars Mielke
Author-email: info@while-ai.org
License-File: LICENSE
